multiparty/__init__.py
multiparty/__main__.py
multiparty/multiparty.py
multiparty-0.0.1.dist-info/METADATA
multiparty-0.0.1.dist-info/WHEEL
multiparty-0.0.1.dist-info/entry_points.txt
multiparty-0.0.1.dist-info/RECORD
